pxly/__init__.py
pxly/cli.py
pxly/core.py
pxly/image_processing.py
pxly/live_video_processing.py
pxly/pixel_conversion.py
pxly/pxly_imports.py
pxly/utils.py
pxly/video_processing.py
pxly-0.1.1.dist-info/METADATA
pxly-0.1.1.dist-info/WHEEL
pxly-0.1.1.dist-info/entry_points.txt
pxly-0.1.1.dist-info/top_level.txt
pxly-0.1.1.dist-info/RECORD
