Metadata-Version: 2.1
Name: pxly
Version: 0.1.1
Summary: Convert videos and images to pixel art, including live streaming.
Author: dumgum82
Author-email: dumgum42@gmail.com
Classifier: Programming Language :: Python :: 3
Classifier: Operating System :: OS Independent
Requires-Dist: opencv-python
Requires-Dist: Pillow
Requires-Dist: numpy
Requires-Dist: mediapipe
Requires-Dist: pyvirtualcam
Requires-Dist: mss
